.gitignore
CHANGES.txt
LICENSE.txt
README.txt
bower.json
setup.py
js/__init__.py
js.spin.egg-info/PKG-INFO
js.spin.egg-info/SOURCES.txt
js.spin.egg-info/dependency_links.txt
js.spin.egg-info/entry_points.txt
js.spin.egg-info/namespace_packages.txt
js.spin.egg-info/not-zip-safe
js.spin.egg-info/requires.txt
js.spin.egg-info/top_level.txt
js/spin/__init__.py
js/spin/test_spin.js.txt
js/spin/resources/jquery.spin.js
js/spin/resources/jquery.spin.min.js
js/spin/resources/spin.js
js/spin/resources/spin.min.js