Metadata-Version: 1.0
Name: js.spin
Version: 2.0.2
Summary: Fanstatic packaging of spin.js
Home-page: https://github.com/disko/js.spin
Author: Andreas Kaiser
Author-email: disko@binary-punks.com
License: BSD
Platform: UNKNOWN
